{"total": 255, "stocks": [{"ticker": "COHR", "ml_score": 0.08176683866851589, "bucket": "growth_tech", "top_feature": "N/A"}, {"ticker": "CRDO", "ml_score": 0.07685309276167576, "bucket": "growth_tech", "top_feature": "N/A"}, {"ticker": "AEM", "ml_score": 0.07612708353790579, "bucket": "real_assets", "top_feature": "N/A"}, {"ticker": "FTI", "ml_score": 0.07492671383212868, "bucket": "real_assets", "top_feature": "N/A"}, {"ticker": "NVDA", "ml_score": 0.07461657757448294, "bucket": "growth_tech", "top_feature": "N/A"}, {"ticker": "KGC", "ml_score": 0.07281215723324025, "bucket": "real_assets", "top_feature": "N/A"}, {"ticker": "FLEX", "ml_score": 0.07203814798052324, "bucket": "growth_tech", "top_feature": "N/A"}, {"ticker": "ARM", "ml_score": 0.07134799650467644, "bucket": "growth_tech", "top_feature": "N/A"}, {"ticker": "JBL", "ml_score": 0.07126085350128425, "bucket": "growth_tech", "top_feature": "N/A"}, {"ticker": "META", "ml_score": 0.07025175385552115, "bucket": "growth_tech", "top_feature": "N/A"}, {"ticker": "GFI", "ml_score": 0.06763288996613774, "bucket": "real_assets", "top_feature": "N/A"}, {"ticker": "CCJ", "ml_score": 0.06607990361115604, "bucket": "real_assets", "top_feature": "N/A"}, {"ticker": "CIEN", "ml_score": 0.061405051682902605, "bucket": "growth_tech", "top_feature": "N/A"}, {"ticker": "KLAC", "ml_score": 0.06106270222082974, "bucket": "growth_tech", "top_feature": "N/A"}, {"ticker": "ANET", "ml_score": 0.06036496311169608, "bucket": "growth_tech", "top_feature": "N/A"}, {"ticker": "DOW", "ml_score": 0.059482833811739924, "bucket": "real_assets", "top_feature": "N/A"}, {"ticker": "FTNT", "ml_score": 0.059429748839273246, "bucket": "growth_tech", "top_feature": "N/A"}, {"ticker": "AMX", "ml_score": 0.05820746983057276, "bucket": "growth_tech", "top_feature": "N/A"}, {"ticker": "GLW", "ml_score": 0.05787725725919968, "bucket": "growth_tech", "top_feature": "N/A"}, {"ticker": "MPWR", "ml_score": 0.05624710993723622, "bucket": "growth_tech", "top_feature": "N/A"}, {"ticker": "MSFT", "ml_score": 0.054103865256301925, "bucket": "growth_tech", "top_feature": "N/A"}, {"ticker": "AVGO", "ml_score": 0.053626945860445474, "bucket": "growth_tech", "top_feature": "N/A"}, {"ticker": "B", "ml_score": 0.05351220179843871, "bucket": "real_assets", "top_feature": "N/A"}, {"ticker": "AMAT", "ml_score": 0.05256468127468163, "bucket": "growth_tech", "top_feature": "N/A"}, {"ticker": "FNV", "ml_score": 0.05129017727998071, "bucket": "real_assets", "top_feature": "N/A"}, {"ticker": "LRCX", "ml_score": 0.05124393678646882, "bucket": "growth_tech", "top_feature": "N/A"}, {"ticker": "E", "ml_score": 0.05017071808382345, "bucket": "real_assets", "top_feature": "N/A"}, {"ticker": "CSCO", "ml_score": 0.05005420941412795, "bucket": "growth_tech", "top_feature": "N/A"}, {"ticker": "DELL", "ml_score": 0.0500460007285802, "bucket": "growth_tech", "top_feature": "N/A"}, {"ticker": "KEYS", "ml_score": 0.04929362874516752, "bucket": "growth_tech", "top_feature": "N/A"}, {"ticker": "EC", "ml_score": 0.04926246929654325, "bucket": "real_assets", "top_feature": "N/A"}, {"ticker": "AMD", "ml_score": 0.04914542012688852, "bucket": "growth_tech", "top_feature": "N/A"}, {"ticker": "ALAB", "ml_score": 0.04904553585990712, "bucket": "growth_tech", "top_feature": "N/A"}, {"ticker": "HOOD", "ml_score": 0.04900618130670662, "bucket": "cyclical", "top_feature": "N/A"}, {"ticker": "ET", "ml_score": 0.048127963253109404, "bucket": "real_assets", "top_feature": "N/A"}, {"ticker": "CHT", "ml_score": 0.04797228148406591, "bucket": "growth_tech", "top_feature": "N/A"}, {"ticker": "CQP", "ml_score": 0.04783511824247778, "bucket": "real_assets", "top_feature": "N/A"}, {"ticker": "DLR", "ml_score": 0.04749136820933503, "bucket": "real_assets", "top_feature": "N/A"}, {"ticker": "GOOGL", "ml_score": 0.047287564443932714, "bucket": "growth_tech", "top_feature": "N/A"}, {"ticker": "BP", "ml_score": 0.04720647600993317, "bucket": "real_assets", "top_feature": "N/A"}, {"ticker": "EQT", "ml_score": 0.047010673205316, "bucket": "real_assets", "top_feature": "N/A"}, {"ticker": "ADP", "ml_score": 0.04679747371601355, "bucket": "growth_tech", "top_feature": "N/A"}, {"ticker": "CTRA", "ml_score": 0.046744197391545214, "bucket": "real_assets", "top_feature": "N/A"}, {"ticker": "KMI", "ml_score": 0.04661486237159657, "bucket": "real_assets", "top_feature": "N/A"}, {"ticker": "F", "ml_score": 0.04655459220123114, "bucket": "cyclical", "top_feature": "N/A"}, {"ticker": "IRM", "ml_score": 0.0462474188720151, "bucket": "real_assets", "top_feature": "N/A"}, {"ticker": "EXR", "ml_score": 0.04618286650184729, "bucket": "real_assets", "top_feature": "N/A"}, {"ticker": "APP", "ml_score": 0.046124361374546716, "bucket": "growth_tech", "top_feature": "N/A"}, {"ticker": "FOXA", "ml_score": 0.04603074212603725, "bucket": "growth_tech", "top_feature": "N/A"}, {"ticker": "BRK-A", "ml_score": 0.0458973704906017, "bucket": "cyclical", "top_feature": "N/A"}, {"ticker": "CVE", "ml_score": 0.04582338425812484, "bucket": "real_assets", "top_feature": "N/A"}, {"ticker": "CVX", "ml_score": 0.04568042407274035, "bucket": "real_assets", "top_feature": "N/A"}, {"ticker": "EQNR", "ml_score": 0.045580828559258046, "bucket": "real_assets", "top_feature": "N/A"}, {"ticker": "CNQ", "ml_score": 0.04556576388744173, "bucket": "real_assets", "top_feature": "N/A"}, {"ticker": "AMRZ", "ml_score": 0.045461605697777234, "bucket": "real_assets", "top_feature": "N/A"}, {"ticker": "MPLX", "ml_score": 0.04537437193606426, "bucket": "real_assets", "top_feature": "N/A"}, {"ticker": "HAL", "ml_score": 0.045352576410896926, "bucket": "real_assets", "top_feature": "N/A"}, {"ticker": "BX", "ml_score": 0.04527555659187853, "bucket": "cyclical", "top_feature": "N/A"}, {"ticker": "ENB", "ml_score": 0.04513946402838817, "bucket": "real_assets", "top_feature": "N/A"}, {"ticker": "ERIC", "ml_score": 0.045136174302966625, "bucket": "growth_tech", "top_feature": "N/A"}, {"ticker": "GM", "ml_score": 0.045023003772665944, "bucket": "cyclical", "top_feature": "N/A"}, {"ticker": "BKR", "ml_score": 0.04495117143463641, "bucket": "real_assets", "top_feature": "N/A"}, {"ticker": "CNI", "ml_score": 0.04488728538955697, "bucket": "cyclical", "top_feature": "N/A"}, {"ticker": "CBRE", "ml_score": 0.04471449338236931, "bucket": "real_assets", "top_feature": "N/A"}, {"ticker": "HDB", "ml_score": 0.04468175204672588, "bucket": "cyclical", "top_feature": "N/A"}, {"ticker": "EPD", "ml_score": 0.04435474710156711, "bucket": "real_assets", "top_feature": "N/A"}, {"ticker": "AMT", "ml_score": 0.04426445781944486, "bucket": "real_assets", "top_feature": "N/A"}, {"ticker": "CTVA", "ml_score": 0.04423761388364658, "bucket": "real_assets", "top_feature": "N/A"}, {"ticker": "MLM", "ml_score": 0.044030249866441745, "bucket": "real_assets", "top_feature": "N/A"}, {"ticker": "HD", "ml_score": 0.043976701463701605, "bucket": "cyclical", "top_feature": "N/A"}, {"ticker": "CLS", "ml_score": 0.0438051586207167, "bucket": "growth_tech", "top_feature": "N/A"}, {"ticker": "ASML", "ml_score": 0.043794682835539216, "bucket": "growth_tech", "top_feature": "N/A"}, {"ticker": "APO", "ml_score": 0.04369333778499285, "bucket": "cyclical", "top_feature": "N/A"}, {"ticker": "LNG", "ml_score": 0.04347844724275213, "bucket": "real_assets", "top_feature": "N/A"}, {"ticker": "CCI", "ml_score": 0.043468588342210776, "bucket": "real_assets", "top_feature": "N/A"}, {"ticker": "INTC", "ml_score": 0.04334044255976228, "bucket": "growth_tech", "top_feature": "N/A"}, {"ticker": "MPC", "ml_score": 0.04320818846883899, "bucket": "real_assets", "top_feature": "N/A"}, {"ticker": "COP", "ml_score": 0.043179124216232434, "bucket": "real_assets", "top_feature": "N/A"}, {"ticker": "GOOG", "ml_score": 0.042908438549017464, "bucket": "growth_tech", "top_feature": "N/A"}, {"ticker": "MELI", "ml_score": 0.042900223838614325, "bucket": "cyclical", "top_feature": "N/A"}, {"ticker": "GS", "ml_score": 0.042865876705564104, "bucket": "cyclical", "top_feature": "N/A"}, {"ticker": "DVN", "ml_score": 0.042734308614806045, "bucket": "real_assets", "top_feature": "N/A"}, {"ticker": "LHX", "ml_score": 0.042715070933295886, "bucket": "cyclical", "top_feature": "N/A"}, {"ticker": "FCX", "ml_score": 0.04264271985013292, "bucket": "real_assets", "top_feature": "N/A"}, {"ticker": "APD", "ml_score": 0.04261758734519146, "bucket": "real_assets", "top_feature": "N/A"}, {"ticker": "ACN", "ml_score": 0.04259673758124514, "bucket": "growth_tech", "top_feature": "N/A"}, {"ticker": "CVNA", "ml_score": 0.04257554715853381, "bucket": "cyclical", "top_feature": "N/A"}, {"ticker": "BLK", "ml_score": 0.0425227026049107, "bucket": "cyclical", "top_feature": "N/A"}, {"ticker": "ICE", "ml_score": 0.04226216729726407, "bucket": "cyclical", "top_feature": "N/A"}, {"ticker": "GFS", "ml_score": 0.04223504080376806, "bucket": "growth_tech", "top_feature": "N/A"}, {"ticker": "IBM", "ml_score": 0.04198289302505478, "bucket": "growth_tech", "top_feature": "N/A"}, {"ticker": "ECL", "ml_score": 0.04196145119276577, "bucket": "real_assets", "top_feature": "N/A"}, {"ticker": "MFC", "ml_score": 0.04195467110508398, "bucket": "cyclical", "top_feature": "N/A"}, {"ticker": "DASH", "ml_score": 0.041846695837910716, "bucket": "cyclical", "top_feature": "N/A"}, {"ticker": "CTAS", "ml_score": 0.041834798449405915, "bucket": "cyclical", "top_feature": "N/A"}, {"ticker": "AFL", "ml_score": 0.04182034376746474, "bucket": "cyclical", "top_feature": "N/A"}, {"ticker": "ABNB", "ml_score": 0.04174975298924888, "bucket": "cyclical", "top_feature": "N/A"}, {"ticker": "CARR", "ml_score": 0.04172289993035465, "bucket": "cyclical", "top_feature": "N/A"}, {"ticker": "HMC", "ml_score": 0.04167801076894811, "bucket": "cyclical", "top_feature": "N/A"}, {"ticker": "HON", "ml_score": 0.04142807271748132, "bucket": "cyclical", "top_feature": "N/A"}, {"ticker": "ITW", "ml_score": 0.04138676075125866, "bucket": "cyclical", "top_feature": "N/A"}, {"ticker": "COR", "ml_score": 0.04129062222753212, "bucket": "defensive", "top_feature": "N/A"}, {"ticker": "JD", "ml_score": 0.041175374161707606, "bucket": "cyclical", "top_feature": "N/A"}, {"ticker": "DAL", "ml_score": 0.04117103995911797, "bucket": "cyclical", "top_feature": "N/A"}, {"ticker": "C", "ml_score": 0.04111065380625214, "bucket": "cyclical", "top_feature": "N/A"}, {"ticker": "AZO", "ml_score": 0.041003080136525705, "bucket": "cyclical", "top_feature": "N/A"}, {"ticker": "ITUB", "ml_score": 0.04090011927446999, "bucket": "cyclical", "top_feature": "N/A"}, {"ticker": "HPE", "ml_score": 0.04077417429719518, "bucket": "growth_tech", "top_feature": "N/A"}, {"ticker": "AXON", "ml_score": 0.04075675083120558, "bucket": "cyclical", "top_feature": "N/A"}, {"ticker": "MCD", "ml_score": 0.040712951075800925, "bucket": "cyclical", "top_feature": "N/A"}, {"ticker": "AME", "ml_score": 0.04070745196469777, "bucket": "cyclical", "top_feature": "N/A"}, {"ticker": "AMZN", "ml_score": 0.040635048809422196, "bucket": "cyclical", "top_feature": "N/A"}, {"ticker": "HEI", "ml_score": 0.040449592417976785, "bucket": "cyclical", "top_feature": "N/A"}, {"ticker": "MMM", "ml_score": 0.04027747853662127, "bucket": "cyclical", "top_feature": "N/A"}, {"ticker": "GWW", "ml_score": 0.04027681766130238, "bucket": "cyclical", "top_feature": "N/A"}, {"ticker": "FER", "ml_score": 0.0402154367680686, "bucket": "cyclical", "top_feature": "N/A"}, {"ticker": "HEI-A", "ml_score": 0.04021458004811007, "bucket": "cyclical", "top_feature": "N/A"}, {"ticker": "AIG", "ml_score": 0.040135180656008844, "bucket": "cyclical", "top_feature": "N/A"}, {"ticker": "DE", "ml_score": 0.04004745187560475, "bucket": "cyclical", "top_feature": "N/A"}, {"ticker": "FITB", "ml_score": 0.03999658157223217, "bucket": "cyclical", "top_feature": "N/A"}, {"ticker": "MA", "ml_score": 0.039944021525452254, "bucket": "cyclical", "top_feature": "N/A"}, {"ticker": "CME", "ml_score": 0.039910487226064675, "bucket": "cyclical", "top_feature": "N/A"}, {"ticker": "AON", "ml_score": 0.039880371982315824, "bucket": "cyclical", "top_feature": "N/A"}, {"ticker": "HBAN", "ml_score": 0.039830165811084686, "bucket": "cyclical", "top_feature": "N/A"}, {"ticker": "IX", "ml_score": 0.039789569643073765, "bucket": "cyclical", "top_feature": "N/A"}, {"ticker": "DOV", "ml_score": 0.039701043034086975, "bucket": "cyclical", "top_feature": "N/A"}, {"ticker": "MS", "ml_score": 0.03969193363901346, "bucket": "cyclical", "top_feature": "N/A"}, {"ticker": "ACGL", "ml_score": 0.03967386622360473, "bucket": "cyclical", "top_feature": "N/A"}, {"ticker": "CUK", "ml_score": 0.03963783384767369, "bucket": "cyclical", "top_feature": "N/A"}, {"ticker": "ETN", "ml_score": 0.03961727102402818, "bucket": "cyclical", "top_feature": "N/A"}, {"ticker": "BSBR", "ml_score": 0.039551449606627584, "bucket": "cyclical", "top_feature": "N/A"}, {"ticker": "BN", "ml_score": 0.03953621335227931, "bucket": "cyclical", "top_feature": "N/A"}, {"ticker": "DDOG", "ml_score": 0.03952921316175259, "bucket": "growth_tech", "top_feature": "N/A"}, {"ticker": "CASY", "ml_score": 0.03951711544244011, "bucket": "cyclical", "top_feature": "N/A"}, {"ticker": "CPNG", "ml_score": 0.03950685875051653, "bucket": "cyclical", "top_feature": "N/A"}, {"ticker": "HIG", "ml_score": 0.03946223792131852, "bucket": "cyclical", "top_feature": "N/A"}, {"ticker": "EMR", "ml_score": 0.03939876310470324, "bucket": "cyclical", "top_feature": "N/A"}, {"ticker": "CPRT", "ml_score": 0.0393940478926746, "bucket": "cyclical", "top_feature": "N/A"}, {"ticker": "IBN", "ml_score": 0.039351389480563874, "bucket": "cyclical", "top_feature": "N/A"}, {"ticker": "JPM", "ml_score": 0.03934763423565354, "bucket": "cyclical", "top_feature": "N/A"}, {"ticker": "CCL", "ml_score": 0.03930824934433908, "bucket": "cyclical", "top_feature": "N/A"}, {"ticker": "CAH", "ml_score": 0.03929564302085354, "bucket": "defensive", "top_feature": "N/A"}, {"ticker": "MCK", "ml_score": 0.03927961860209318, "bucket": "defensive", "top_feature": "N/A"}, {"ticker": "CMG", "ml_score": 0.03916027643605058, "bucket": "cyclical", "top_feature": "N/A"}, {"ticker": "EXPE", "ml_score": 0.039159546210980015, "bucket": "cyclical", "top_feature": "N/A"}, {"ticker": "DHI", "ml_score": 0.039143915091652534, "bucket": "cyclical", "top_feature": "N/A"}, {"ticker": "CB", "ml_score": 0.03912663378781367, "bucket": "cyclical", "top_feature": "N/A"}, {"ticker": "CMCSA", "ml_score": 0.03910469319007134, "bucket": "growth_tech", "top_feature": "N/A"}, {"ticker": "CP", "ml_score": 0.03907382426956865, "bucket": "cyclical", "top_feature": "N/A"}, {"ticker": "HUBB", "ml_score": 0.039039666393429824, "bucket": "cyclical", "top_feature": "N/A"}, {"ticker": "BCS", "ml_score": 0.03901278576281171, "bucket": "cyclical", "top_feature": "N/A"}, {"ticker": "MRSH", "ml_score": 0.03898608833650743, "bucket": "cyclical", "top_feature": "N/A"}, {"ticker": "COIN", "ml_score": 0.03896377898737608, "bucket": "cyclical", "top_feature": "N/A"}, {"ticker": "ALL", "ml_score": 0.03892660402202066, "bucket": "cyclical", "top_feature": "N/A"}, {"ticker": "EBAY", "ml_score": 0.03883856581493573, "bucket": "cyclical", "top_feature": "N/A"}, {"ticker": "HLT", "ml_score": 0.03868711941627078, "bucket": "cyclical", "top_feature": "N/A"}, {"ticker": "BRK-B", "ml_score": 0.03868104545671224, "bucket": "cyclical", "top_feature": "N/A"}, {"ticker": "MCO", "ml_score": 0.038677021194073895, "bucket": "cyclical", "top_feature": "N/A"}, {"ticker": "AMP", "ml_score": 0.03864713129133182, "bucket": "cyclical", "top_feature": "N/A"}, {"ticker": "FDX", "ml_score": 0.038609024219736394, "bucket": "cyclical", "top_feature": "N/A"}, {"ticker": "COF", "ml_score": 0.03858945759160531, "bucket": "cyclical", "top_feature": "N/A"}, {"ticker": "LOW", "ml_score": 0.038498887069832004, "bucket": "cyclical", "top_feature": "N/A"}, {"ticker": "CMI", "ml_score": 0.038455578651381536, "bucket": "cyclical", "top_feature": "N/A"}, {"ticker": "GE", "ml_score": 0.03835671663408321, "bucket": "cyclical", "top_feature": "N/A"}, {"ticker": "MSCI", "ml_score": 0.03835458127483158, "bucket": "cyclical", "top_feature": "N/A"}, {"ticker": "AJG", "ml_score": 0.038321787436226815, "bucket": "cyclical", "top_feature": "N/A"}, {"ticker": "GD", "ml_score": 0.038296088036037935, "bucket": "cyclical", "top_feature": "N/A"}, {"ticker": "BKNG", "ml_score": 0.038140617818095364, "bucket": "cyclical", "top_feature": "N/A"}, {"ticker": "CAT", "ml_score": 0.03812125056433027, "bucket": "cyclical", "top_feature": "N/A"}, {"ticker": "MCHP", "ml_score": 0.038042882681094604, "bucket": "growth_tech", "top_feature": "N/A"}, {"ticker": "FAST", "ml_score": 0.0378914672556516, "bucket": "cyclical", "top_feature": "N/A"}, {"ticker": "BK", "ml_score": 0.03786578636244891, "bucket": "cyclical", "top_feature": "N/A"}, {"ticker": "HSBC", "ml_score": 0.03778630108351633, "bucket": "cyclical", "top_feature": "N/A"}, {"ticker": "CSX", "ml_score": 0.03777429300850637, "bucket": "cyclical", "top_feature": "N/A"}, {"ticker": "AXP", "ml_score": 0.03777401511377828, "bucket": "cyclical", "top_feature": "N/A"}, {"ticker": "LYV", "ml_score": 0.037719663236791226, "bucket": "growth_tech", "top_feature": "N/A"}, {"ticker": "JCI", "ml_score": 0.03761489104940107, "bucket": "cyclical", "top_feature": "N/A"}, {"ticker": "LVS", "ml_score": 0.03755444055228119, "bucket": "cyclical", "top_feature": "N/A"}, {"ticker": "BAC", "ml_score": 0.03743145353822284, "bucket": "cyclical", "top_feature": "N/A"}, {"ticker": "BABA", "ml_score": 0.03723135069278288, "bucket": "cyclical", "top_feature": "N/A"}, {"ticker": "BAM", "ml_score": 0.03689737098406157, "bucket": "cyclical", "top_feature": "N/A"}, {"ticker": "ADSK", "ml_score": 0.0367774223530485, "bucket": "growth_tech", "top_feature": "N/A"}, {"ticker": "MET", "ml_score": 0.0367453748239817, "bucket": "cyclical", "top_feature": "N/A"}, {"ticker": "LITE", "ml_score": 0.03657845375629818, "bucket": "growth_tech", "top_feature": "N/A"}, {"ticker": "ABEV", "ml_score": 0.03656648027896203, "bucket": "defensive", "top_feature": "N/A"}, {"ticker": "DB", "ml_score": 0.03640440966005945, "bucket": "cyclical", "top_feature": "N/A"}, {"ticker": "BA", "ml_score": 0.0363429447669319, "bucket": "cyclical", "top_feature": "N/A"}, {"ticker": "CM", "ml_score": 0.03622462919940523, "bucket": "cyclical", "top_feature": "N/A"}, {"ticker": "INFY", "ml_score": 0.035899337641218235, "bucket": "growth_tech", "top_feature": "N/A"}, {"ticker": "MFG", "ml_score": 0.035876771060972756, "bucket": "cyclical", "top_feature": "N/A"}, {"ticker": "BE", "ml_score": 0.03582413488127094, "bucket": "cyclical", "top_feature": "N/A"}, {"ticker": "KB", "ml_score": 0.03557281261226799, "bucket": "cyclical", "top_feature": "N/A"}, {"ticker": "ADM", "ml_score": 0.03488876305702267, "bucket": "defensive", "top_feature": "N/A"}, {"ticker": "EXC", "ml_score": 0.03304440887642725, "bucket": "defensive", "top_feature": "N/A"}, {"ticker": "EA", "ml_score": 0.03284078758951583, "bucket": "growth_tech", "top_feature": "N/A"}, {"ticker": "MO", "ml_score": 0.03255765496906836, "bucket": "defensive", "top_feature": "N/A"}, {"ticker": "GRMN", "ml_score": 0.032178092942716154, "bucket": "growth_tech", "top_feature": "N/A"}, {"ticker": "HCA", "ml_score": 0.031592169336493184, "bucket": "defensive", "top_feature": "N/A"}, {"ticker": "FMX", "ml_score": 0.03085943160078734, "bucket": "defensive", "top_feature": "N/A"}, {"ticker": "EIX", "ml_score": 0.030830691379464745, "bucket": "defensive", "top_feature": "N/A"}, {"ticker": "ADI", "ml_score": 0.03047638850160148, "bucket": "growth_tech", "top_feature": "N/A"}, {"ticker": "CRWV", "ml_score": 0.030420089134981964, "bucket": "growth_tech", "top_feature": "N/A"}, {"ticker": "BTI", "ml_score": 0.029743241271266305, "bucket": "defensive", "top_feature": "N/A"}, {"ticker": "ABBV", "ml_score": 0.028879367447728576, "bucket": "defensive", "top_feature": "N/A"}, {"ticker": "MRVL", "ml_score": 0.02884443697799357, "bucket": "growth_tech", "top_feature": "N/A"}, {"ticker": "AXIA", "ml_score": 0.028645333354763103, "bucket": "defensive", "top_feature": "N/A"}, {"ticker": "AMGN", "ml_score": 0.028510007958548203, "bucket": "defensive", "top_feature": "N/A"}, {"ticker": "ISRG", "ml_score": 0.02843111120813809, "bucket": "defensive", "top_feature": "N/A"}, {"ticker": "A", "ml_score": 0.028401879197841092, "bucket": "defensive", "top_feature": "N/A"}, {"ticker": "BMY", "ml_score": 0.027981830023448537, "bucket": "defensive", "top_feature": "N/A"}, {"ticker": "ETR", "ml_score": 0.027523018248238697, "bucket": "defensive", "top_feature": "N/A"}, {"ticker": "KR", "ml_score": 0.027348142665148335, "bucket": "defensive", "top_feature": "N/A"}, {"ticker": "KHC", "ml_score": 0.027305164371411134, "bucket": "defensive", "top_feature": "N/A"}, {"ticker": "DTE", "ml_score": 0.026996658415375147, "bucket": "defensive", "top_feature": "N/A"}, {"ticker": "MNST", "ml_score": 0.026937142122399216, "bucket": "defensive", "top_feature": "N/A"}, {"ticker": "DHR", "ml_score": 0.026450595513335833, "bucket": "defensive", "top_feature": "N/A"}, {"ticker": "GEHC", "ml_score": 0.026422821793082835, "bucket": "defensive", "top_feature": "N/A"}, {"ticker": "KMB", "ml_score": 0.026383148501499483, "bucket": "defensive", "top_feature": "N/A"}, {"ticker": "CEG", "ml_score": 0.02622540721944672, "bucket": "defensive", "top_feature": "N/A"}, {"ticker": "MDLN", "ml_score": 0.02617766363730086, "bucket": "defensive", "top_feature": "N/A"}, {"ticker": "AAPL", "ml_score": 0.02599919664601218, "bucket": "growth_tech", "top_feature": "N/A"}, {"ticker": "HSY", "ml_score": 0.025943508428291698, "bucket": "defensive", "top_feature": "N/A"}, {"ticker": "MRK", "ml_score": 0.025936678587831184, "bucket": "defensive", "top_feature": "N/A"}, {"ticker": "MDLZ", "ml_score": 0.025928108498229345, "bucket": "defensive", "top_feature": "N/A"}, {"ticker": "CL", "ml_score": 0.025927895670278044, "bucket": "defensive", "top_feature": "N/A"}, {"ticker": "CCEP", "ml_score": 0.02581860976159207, "bucket": "defensive", "top_feature": "N/A"}, {"ticker": "KO", "ml_score": 0.02578169915672357, "bucket": "defensive", "top_feature": "N/A"}, {"ticker": "GSK", "ml_score": 0.025745704809390244, "bucket": "defensive", "top_feature": "N/A"}, {"ticker": "ED", "ml_score": 0.025628345284022004, "bucket": "defensive", "top_feature": "N/A"}, {"ticker": "EL", "ml_score": 0.025618348976371223, "bucket": "defensive", "top_feature": "N/A"}, {"ticker": "BUD", "ml_score": 0.025480785757826384, "bucket": "defensive", "top_feature": "N/A"}, {"ticker": "ES", "ml_score": 0.02536666727589942, "bucket": "defensive", "top_feature": "N/A"}, {"ticker": "CVS", "ml_score": 0.02511803168744444, "bucket": "defensive", "top_feature": "N/A"}, {"ticker": "KVUE", "ml_score": 0.024944581588937385, "bucket": "defensive", "top_feature": "N/A"}, {"ticker": "GILD", "ml_score": 0.024870110172381173, "bucket": "defensive", "top_feature": "N/A"}, {"ticker": "MDT", "ml_score": 0.024845022151129777, "bucket": "defensive", "top_feature": "N/A"}, {"ticker": "ATO", "ml_score": 0.02482631788640888, "bucket": "defensive", "top_feature": "N/A"}, {"ticker": "CI", "ml_score": 0.02468497866381033, "bucket": "defensive", "top_feature": "N/A"}, {"ticker": "FTS", "ml_score": 0.024684637163434737, "bucket": "defensive", "top_feature": "N/A"}, {"ticker": "DUK", "ml_score": 0.02467350393760442, "bucket": "defensive", "top_feature": "N/A"}, {"ticker": "FE", "ml_score": 0.024507892971224833, "bucket": "defensive", "top_feature": "N/A"}, {"ticker": "JNJ", "ml_score": 0.024434078870871376, "bucket": "defensive", "top_feature": "N/A"}, {"ticker": "AEE", "ml_score": 0.02423658901671817, "bucket": "defensive", "top_feature": "N/A"}, {"ticker": "ALNY", "ml_score": 0.024036508536732233, "bucket": "defensive", "top_feature": "N/A"}, {"ticker": "LLY", "ml_score": 0.02393386970970083, "bucket": "defensive", "top_feature": "N/A"}, {"ticker": "CNP", "ml_score": 0.023706033931134192, "bucket": "defensive", "top_feature": "N/A"}, {"ticker": "IDXX", "ml_score": 0.02370372147032081, "bucket": "defensive", "top_feature": "N/A"}, {"ticker": "EW", "ml_score": 0.023673029480038743, "bucket": "defensive", "top_feature": "N/A"}, {"ticker": "AEP", "ml_score": 0.023643295291801154, "bucket": "defensive", "top_feature": "N/A"}, {"ticker": "D", "ml_score": 0.023561339136313586, "bucket": "defensive", "top_feature": "N/A"}, {"ticker": "BSX", "ml_score": 0.023560008088616205, "bucket": "defensive", "top_feature": "N/A"}, {"ticker": "HUM", "ml_score": 0.023500168662422438, "bucket": "defensive", "top_feature": "N/A"}, {"ticker": "ALC", "ml_score": 0.023392251918715103, "bucket": "defensive", "top_feature": "N/A"}, {"ticker": "DEO", "ml_score": 0.023200738853587897, "bucket": "defensive", "top_feature": "N/A"}, {"ticker": "KDP", "ml_score": 0.023047784409727108, "bucket": "defensive", "top_feature": "N/A"}]}